powerline_taskwarrior/__init__.py
powerline_taskwarrior/segments.py
powerline_taskwarrior-2.0.0.dist-info/LICENSE
powerline_taskwarrior-2.0.0.dist-info/WHEEL
powerline_taskwarrior-2.0.0.dist-info/METADATA
powerline_taskwarrior-2.0.0.dist-info/RECORD
