Metadata-Version: 2.1
Name: powerline-taskwarrior
Version: 2.0.0
Summary: Powerline segments for showing information from the Taskwarrior task manager
Home-page: https://github.com/zebradil/powerline-taskwarrior
License: MIT
Keywords: powerline,taskwarrior,powerline-segment,taskwarrior-segment,powerline-taskwarrior
Author: German Lashevich
Author-email: german.lashevich@gmail.com
Requires-Python: >=3.7,<4.0
Classifier: Environment :: Console
Classifier: Intended Audience :: Developers
Classifier: License :: OSI Approved :: MIT License
Classifier: Programming Language :: Python :: 3
Classifier: Programming Language :: Python :: 3.10
Classifier: Programming Language :: Python :: 3.7
Classifier: Programming Language :: Python :: 3.8
Classifier: Programming Language :: Python :: 3.9
Classifier: Topic :: Terminals
Requires-Dist: powerline-status (>=2.7,<3.0)
Project-URL: Documentation, https://github.com/Zebradil/powerline-taskwarrior/blob/master/README.md
Project-URL: Repository, https://github.com/zebradil/powerline-taskwarrior
